spylizard/__init__.py
spylizard-0.32.dist-info/LICENSE
spylizard-0.32.dist-info/METADATA
spylizard-0.32.dist-info/WHEEL
spylizard-0.32.dist-info/top_level.txt
spylizard-0.32.dist-info/RECORD
