Metadata-Version: 2.1
Name: spylizard
Version: 0.32
Summary: A python wrapper for spylizard
Home-page: https://github.com/halbux/sparselizard-users
Author: Hamid Badi
Author-email: badi.hamid@gmail.com
License: GNU GPLv2+
Classifier: Development Status :: 1 - Planning
Classifier: Intended Audience :: Science/Research
Classifier: License :: OSI Approved :: BSD License
Classifier: Operating System :: POSIX :: Linux
Classifier: Programming Language :: Python :: 2
Classifier: Programming Language :: Python :: 2.7
Classifier: Programming Language :: Python :: 3
Classifier: Programming Language :: Python :: 3.4
Classifier: Programming Language :: Python :: 3.5
License-File: LICENSE
